optimex/__init__.py
optimex/converter.py
optimex/lca_processor.py
optimex/optimizer.py
optimex/postprocessing.py
optimex-0.3.0.dist-info/licenses/LICENSE
optimex-0.3.0.dist-info/METADATA
optimex-0.3.0.dist-info/WHEEL
optimex-0.3.0.dist-info/top_level.txt
optimex-0.3.0.dist-info/RECORD
