Metadata-Version: 2.4
Name: optimex
Version: 0.3.0
Summary: Time-Explicit Life Cycle Optimization
Author-email: Timo Diepers <timo.diepers@ltt.rwth-aachen.de>, Jan Tautorus <jan.tautorus@rwth-aachen.de>
Maintainer-email: Timo Diepers <timo.diepers@ltt.rwth-aachen.de>
Project-URL: source, https://github.com/TimoDiepers/optimex
Project-URL: homepage, https://github.com/TimoDiepers/optimex
Project-URL: tracker, https://github.com/TimoDiepers/optimex/issues
Classifier: Development Status :: 4 - Beta
Classifier: Programming Language :: Python
Classifier: Programming Language :: Python :: 3
Classifier: Programming Language :: Python :: 3.9
Classifier: Programming Language :: Python :: 3.10
Classifier: Programming Language :: Python :: 3.11
Classifier: Programming Language :: Python :: 3.12
Classifier: Natural Language :: English
Classifier: Operating System :: OS Independent
Classifier: Topic :: Scientific/Engineering
Requires-Python: >=3.9
License-File: LICENSE
Requires-Dist: dynamic-characterization
Requires-Dist: brightway25
Requires-Dist: tdqm
Requires-Dist: pyomo
Requires-Dist: pyyaml
Requires-Dist: bw-temporalis
Provides-Extra: testing
Requires-Dist: optimex; extra == "testing"
Requires-Dist: pytest; extra == "testing"
Requires-Dist: pytest-cov; extra == "testing"
Requires-Dist: python-coveralls; extra == "testing"
Provides-Extra: dev
Requires-Dist: build; extra == "dev"
Requires-Dist: pre-commit; extra == "dev"
Requires-Dist: pylint; extra == "dev"
Requires-Dist: pytest; extra == "dev"
Requires-Dist: pytest-cov; extra == "dev"
Requires-Dist: pytest-randomly; extra == "dev"
Requires-Dist: setuptools; extra == "dev"
Dynamic: license-file
